{
  "year": 2016,
  "winners": [
    {
      "name": "Amazon.com Inc.",
      "ticker": "AMZN",
      "type": "stock",
      "score": 85,
      "weight": 0.2833333333333333
    },
    {
      "name": "NVIDIA Corporation",
      "ticker": "NVDA",
      "type": "stock",
      "score": 78,
      "weight": 0.26
    },
    {
      "name": "Exxon Mobil Corporation",
      "ticker": "XOM",
      "type": "stock",
      "score": 72,
      "weight": 0.24
    },
    {
      "name": "Bitcoin",
      "ticker": "BTC",
      "type": "crypto asset",
      "score": 65,
      "weight": 0.21666666666666667
    }
  ],
  "generatedAt": "2026-02-13T05:43:36.428Z"
}
